<?xml version="1.0" encoding="utf-8" ?><dwsync><file name="plugin-update-checker-it_IT.mo" server="healings.mixh.jp/public_html/nagai-architects/wp-content/" local="3645139192" remote="3650598000" Dst="-1" /><file name="plugin-update-checker-sl_SI.po" server="healings.mixh.jp/public_html/nagai-architects/wp-content/" local="3645139192" remote="3650598000" Dst="-1" /><file name="plugin-update-checker-cs_CZ.po" server="healings.mixh.jp/public_html/nagai-architects/wp-content/" local="3645139192" remote="3650598000" Dst="-1" /><file name="plugin-update-checker-nl_NL.po" server="healings.mixh.jp/public_html/nagai-architects/wp-content/" local="3645139192" remote="3650598000" Dst="-1" /><file name="plugin-update-checker-fr_FR.po" server="healings.mixh.jp/public_html/nagai-architects/wp-content/" local="3645139192" remote="3650598000" Dst="-1" /><file name="plugin-update-checker-de_DE.mo" server="healings.mixh.jp/public_html/nagai-architects/wp-content/" local="3645139192" remote="3650598000" Dst="-1" /><file name="plugin-update-checker-fa_IR.po" server="healings.mixh.jp/public_html/nagai-architects/wp-content/" local="3645139192" remote="3650598000" Dst="-1" /><file name="plugin-update-checker-pt_BR.po" server="healings.mixh.jp/public_html/nagai-architects/wp-content/" local="3645139192" remote="3650598000" Dst="-1" /><file name="plugin-update-checker-hu_HU.po" server="healings.mixh.jp/public_html/nagai-architects/wp-content/" local="3645139192" remote="3650598000" Dst="-1" /><file name="plugin-update-checker-nl_BE.po" server="healings.mixh.jp/public_html/nagai-architects/wp-content/" local="3645139192" remote="3650598000" Dst="-1" /><file name="plugin-update-checker-ja.mo" server="healings.mixh.jp/public_html/nagai-architects/wp-content/" local="3645139192" remote="3650598000" Dst="-1" /><file name="plugin-update-checker-fr_CA.po" server="healings.mixh.jp/public_html/nagai-architects/wp-content/" local="3645139192" remote="3650598000" Dst="-1" /><file name="plugin-update-checker-sv_SE.mo" server="healings.mixh.jp/public_html/nagai-architects/wp-content/" local="3645139192" remote="3650598000" Dst="-1" /><file name="plugin-update-checker.pot" server="healings.mixh.jp/public_html/nagai-architects/wp-content/" local="3645139192" remote="3650598000" Dst="-1" /><file name="plugin-update-checker-da_DK.mo" server="healings.mixh.jp/public_html/nagai-architects/wp-content/" local="3645139192" remote="3650598000" Dst="-1" /><file name="plugin-update-checker-fa_IR.mo" server="healings.mixh.jp/public_html/nagai-architects/wp-content/" local="3645139192" remote="3650598000" Dst="-1" /><file name="plugin-update-checker-pt_BR.mo" server="healings.mixh.jp/public_html/nagai-architects/wp-content/" local="3645139192" remote="3650598000" Dst="-1" /><file name="plugin-update-checker-de_DE.po" server="healings.mixh.jp/public_html/nagai-architects/wp-content/" local="3645139192" remote="3650598000" Dst="-1" /><file name="plugin-update-checker-sl_SI.mo" server="healings.mixh.jp/public_html/nagai-architects/wp-content/" local="3645139192" remote="3650598000" Dst="-1" /><file name="plugin-update-checker-nl_NL.mo" server="healings.mixh.jp/public_html/nagai-architects/wp-content/" local="3645139192" remote="3650598000" Dst="-1" /><file name="plugin-update-checker-fr_FR.mo" server="healings.mixh.jp/public_html/nagai-architects/wp-content/" local="3645139192" remote="3650598000" Dst="-1" /><file name="plugin-update-checker-it_IT.po" server="healings.mixh.jp/public_html/nagai-architects/wp-content/" local="3645139192" remote="3650598000" Dst="-1" /><file name="plugin-update-checker-cs_CZ.mo" server="healings.mixh.jp/public_html/nagai-architects/wp-content/" local="3645139192" remote="3650598000" Dst="-1" /><file name="plugin-update-checker-sv_SE.po" server="healings.mixh.jp/public_html/nagai-architects/wp-content/" local="3645139192" remote="3650598000" Dst="-1" /><file name="plugin-update-checker-da_DK.po" server="healings.mixh.jp/public_html/nagai-architects/wp-content/" local="3645139192" remote="3650598000" Dst="-1" /><file name="plugin-update-checker-fr_CA.mo" server="healings.mixh.jp/public_html/nagai-architects/wp-content/" local="3645139192" remote="3650598000" Dst="-1" /><file name="plugin-update-checker-hu_HU.mo" server="healings.mixh.jp/public_html/nagai-architects/wp-content/" local="3645139192" remote="3650598000" Dst="-1" /><file name="plugin-update-checker-nl_BE.mo" server="healings.mixh.jp/public_html/nagai-architects/wp-content/" local="3645139192" remote="3650598000" Dst="-1" /><file name="plugin-update-checker-ja.po" server="healings.mixh.jp/public_html/nagai-architects/wp-content/" local="3645139192" remote="3650598000" Dst="-1" /></dwsync>